fpsql/__init__.py
fpsql-1.0.26.dist-info/LICENSE
fpsql-1.0.26.dist-info/METADATA
fpsql-1.0.26.dist-info/WHEEL
fpsql-1.0.26.dist-info/RECORD
